vikivission/Vission.py
vikivission/__init__.py
viki_ai_vision-0.0.1.dist-info/License.TXT
viki_ai_vision-0.0.1.dist-info/METADATA
viki_ai_vision-0.0.1.dist-info/WHEEL
viki_ai_vision-0.0.1.dist-info/top_level.txt
viki_ai_vision-0.0.1.dist-info/RECORD
